[
  {"title":"Deeptracy Dashboard 1.0.0", "language":"javascript", "_id":"58f5ceb3e14b0a10074c6daf", "lastScan":"2017-11-11", "repo":"https://github.com/BBVA/deeptracy-dashboard.git" },
  {"title":"Demo Node.js 1.0.0", "language":"nodejs", "_id":"58f5ceb3e14b0a10074c6dae", "lastScan":"2017-11-11", "repo":"https://github.com/BBVA/deeptracy-dashboard.git" },
  {"title":"Demo Python 1.0.0", "language":"python", "_id":"58f5ceb3e14b0a10074c6dad", "lastScan":"2017-11-11", "repo":"https://github.com/BBVA/deeptracy-api.git" },
  {"title":"Demo Java 1.0.0", "language":"java", "_id":"58f5ceb3e14b0a10074c6dac", "lastScan":"2017-11-11", "repo":"https://github.com/BBVA/deeptracy-dashboard.git" },
  {"title":"Demo Go 1.0.0", "language":"javascript", "_id":"58f5ceb3e14b0a10074c6dab", "lastScan":"2017-11-11", "repo":"https://github.com/BBVA/deeptracy-dashboard.git" }
]
